ipsrvdb/__init__.py
ipsrvdb/ipsrvdb.py
ipsrvdb-1.0.2.dist-info/LICENSE
ipsrvdb-1.0.2.dist-info/METADATA
ipsrvdb-1.0.2.dist-info/WHEEL
ipsrvdb-1.0.2.dist-info/top_level.txt
ipsrvdb-1.0.2.dist-info/RECORD
