Metadata-Version: 2.1
Name: ipsrvdb
Version: 1.0.2
Summary: IPsrv ipsrv db parsing library
Home-page: https://github.com/ipsrv/ipsrvdb-python
Author: ipsrv.net
Author-email: admin@ipsrv.net
Maintainer: ipsrv
Maintainer-email: admin@ipsrv.net
License: Apache License Version 2.0
Platform: all
